arthub_login_widgets/__init__.py
arthub_login_widgets/__version__.py
arthub_login_widgets/constants.py
arthub_login_widgets/core.py
arthub_login_widgets/exception.py
arthub_login_widgets/filesystem.py
arthub_login_widgets/resources/__init__.py
arthub_login_widgets/resources/client/LICENSE.electron.txt
arthub_login_widgets/resources/client/LICENSES.chromium.html
arthub_login_widgets/resources/client/arthub-tools.exe
arthub_login_widgets/resources/client/chrome_100_percent.pak
arthub_login_widgets/resources/client/chrome_200_percent.pak
arthub_login_widgets/resources/client/d3dcompiler_47.dll
arthub_login_widgets/resources/client/ffmpeg.dll
arthub_login_widgets/resources/client/icudtl.dat
arthub_login_widgets/resources/client/libEGL.dll
arthub_login_widgets/resources/client/libGLESv2.dll
arthub_login_widgets/resources/client/resources.pak
arthub_login_widgets/resources/client/snapshot_blob.bin
arthub_login_widgets/resources/client/v8_context_snapshot.bin
arthub_login_widgets/resources/client/vk_swiftshader.dll
arthub_login_widgets/resources/client/vk_swiftshader_icd.json
arthub_login_widgets/resources/client/locales/am.pak
arthub_login_widgets/resources/client/locales/ar.pak
arthub_login_widgets/resources/client/locales/bg.pak
arthub_login_widgets/resources/client/locales/bn.pak
arthub_login_widgets/resources/client/locales/ca.pak
arthub_login_widgets/resources/client/locales/cs.pak
arthub_login_widgets/resources/client/locales/da.pak
arthub_login_widgets/resources/client/locales/de.pak
arthub_login_widgets/resources/client/locales/el.pak
arthub_login_widgets/resources/client/locales/en-GB.pak
arthub_login_widgets/resources/client/locales/en-US.pak
arthub_login_widgets/resources/client/locales/es-419.pak
arthub_login_widgets/resources/client/locales/es.pak
arthub_login_widgets/resources/client/locales/et.pak
arthub_login_widgets/resources/client/locales/fa.pak
arthub_login_widgets/resources/client/locales/fi.pak
arthub_login_widgets/resources/client/locales/fil.pak
arthub_login_widgets-1.0.0.dist-info/METADATA
arthub_login_widgets-1.0.0.dist-info/WHEEL
arthub_login_widgets-1.0.0.dist-info/top_level.txt
arthub_login_widgets-1.0.0.dist-info/RECORD
