Metadata-Version: 2.1
Name: arthub-login-widgets
Version: 1.0.0
Summary: A Qt Widget for login ArtHub.
Home-page: https://git.woa.com/lightbox/internal/arthub_login_widgets
Author: Joey Ding
Author-email: joeyding@tencent.com
Classifier: Programming Language :: Python
Classifier: Programming Language :: Python :: 2
Classifier: Programming Language :: Python :: 3
Requires-Dist: arthub-api >=1.9.2
Requires-Dist: platformdirs >=4
Requires-Dist: pyyaml >=6
Requires-Dist: Qt.py
